[{"name": "Ruby Gillman, Teenage Kraken", "url": "https://ak.sv/movie/8831/ruby-gillman-teenage-kraken", "image_url": "https://img.downet.net/thumb/178x260/uploads/t04rG.jpeg", "year": 2023, "genre": "انمي, اكشن, مغامرة", "rating": 5.8, "createdAt": "2026-02-26T11:46:13"}, {"name": "My Heart Puppy", "url": "https://ak.sv/movie/8833/my-heart-puppy", "image_url": "https://img.downet.net/thumb/178x260/uploads/FiytQ.jpg", "year": 2023, "genre": "كوميدي, عائلي, دراما", "rating": 7.5, "createdAt": "2026-02-26T11:46:19"}, {"name": "Ratsasan", "url": "https://ak.sv/movie/8824/ratsasan", "image_url": "https://img.downet.net/thumb/178x260/uploads/yGXNX.jpg", "year": 2018, "genre": "اكشن, دراما, جريمة", "rating": 8.3, "createdAt": "2026-02-26T11:46:19"}, {"name": "Bear Man", "url": "https://ak.sv/movie/8813/bear-man", "image_url": "https://img.downet.net/thumb/178x260/uploads/YEXvT.jpg", "year": 2023, "genre": "اكشن, كوميدي", "rating": 5.9, "createdAt": "2026-02-26T11:46:19"}, {"name": "The Flood", "url": "https://ak.sv/movie/8811/the-flood", "image_url": "https://img.downet.net/thumb/178x260/uploads/IpI2j.jpg", "year": 2023, "genre": "اكشن, اثارة, رعب", "rating": 5.7, "createdAt": "2026-02-26T11:46:19"}, {"name": "Disquiet", "url": "https://ak.sv/movie/8812/disquiet", "image_url": "https://img.downet.net/thumb/178x260/uploads/Ox4NK.jpg", "year": 2023, "genre": "اثارة", "rating": 3.9, "createdAt": "2026-02-26T11:46:19"}, {"name": "Jericho Ridge", "url": "https://ak.sv/movie/8810/jericho-ridge", "image_url": "https://img.downet.net/thumb/178x260/uploads/6ueMy.jpg", "year": 2022, "genre": "اكشن, اثارة", "rating": 5.6, "createdAt": "2026-02-26T11:46:19"}, {"name": "A Hundred Flowers", "url": "https://ak.sv/movie/8809/a-hundred-flowers", "image_url": "https://img.downet.net/thumb/178x260/uploads/O6ir3.jpg", "year": 2022, "genre": "دراما", "rating": 6.5, "createdAt": "2026-02-26T11:46:19"}, {"name": "Call Her King", "url": "https://ak.sv/movie/8808/call-her-king", "image_url": "https://img.downet.net/thumb/178x260/uploads/D4YQk.jpg", "year": 2023, "genre": "اكشن, اثارة", "rating": 4.3, "createdAt": "2026-02-26T11:46:19"}, {"name": "As Certain as Death", "url": "https://ak.sv/movie/8807/as-certain-as-death", "image_url": "https://img.downet.net/thumb/178x260/uploads/eLw7l.jpg", "year": 2023, "genre": "رعب", "rating": 4.9, "createdAt": "2026-02-26T11:46:19"}, {"name": "Day Zero", "url": "https://ak.sv/movie/8806/day-zero", "image_url": "https://img.downet.net/thumb/178x260/uploads/BuGpy.jpg", "year": 2022, "genre": "اكشن, رعب", "rating": 5.4, "createdAt": "2026-02-26T11:46:19"}, {"name": "Quicksand", "url": "https://ak.sv/movie/8805/quicksand", "image_url": "https://img.downet.net/thumb/178x260/uploads/IZgeV.jpg", "year": 2023, "genre": "اثارة", "rating": 5.2, "createdAt": "2026-02-26T11:46:19"}, {"name": "God Is a Bullet", "url": "https://ak.sv/movie/8803/god-is-a-bullet", "image_url": "https://img.downet.net/thumb/178x260/uploads/BCVSD.jpg", "year": 2023, "genre": "اكشن, رعب, جريمة", "rating": 5.9, "createdAt": "2026-02-26T11:46:19"}, {"name": "Gray Matter", "url": "https://ak.sv/movie/8802/gray-matter", "image_url": "https://img.downet.net/thumb/178x260/uploads/58bYT.jpg", "year": 2023, "genre": "اثارة, خيال علمي, دراما", "rating": 4.6, "createdAt": "2026-02-26T11:46:19"}, {"name": "أساليب الحب 2", "url": "https://ak.sv/movie/8804/أساليب-الحب-2", "image_url": "https://img.downet.net/thumb/178x260/uploads/xZeYy.jpg", "year": 2023, "genre": "مدبلج, NETFLIX, كوميدي, رومانسي", "rating": 7.2, "createdAt": "2026-02-26T11:46:19"}, {"name": "Love Tactics 2", "url": "https://ak.sv/movie/8801/love-tactics-2", "image_url": "https://img.downet.net/thumb/178x260/uploads/VSvyG.jpg", "year": 2023, "genre": "كوميدي, رومانسي", "rating": 7.2, "createdAt": "2026-02-26T11:46:19"}, {"name": "Thandatti", "url": "https://ak.sv/movie/8798/thandatti", "image_url": "https://img.downet.net/thumb/178x260/uploads/q0GCZ.jpg", "year": 2023, "genre": "كوميدي, دراما", "rating": 7.5, "createdAt": "2026-02-26T11:46:19"}, {"name": "Familia", "url": "https://ak.sv/movie/8799/familia", "image_url": "https://img.downet.net/thumb/178x260/uploads/0CQ26.jpg", "year": 2023, "genre": "دراما", "rating": 6.3, "createdAt": "2026-02-26T11:46:19"}, {"name": "Walking Against the Rain", "url": "https://ak.sv/movie/8797/walking-against-the-rain", "image_url": "https://img.downet.net/thumb/178x260/uploads/acQNd.jpg", "year": 2022, "genre": "فانتازيا, دراما, رعب", "rating": 6.4, "createdAt": "2026-02-26T11:46:19"}, {"name": "Cabin Girl", "url": "https://ak.sv/movie/8796/cabin-girl", "image_url": "https://img.downet.net/thumb/178x260/uploads/4LWBL.jpg", "year": 2023, "genre": "اثارة", "rating": 6.1, "createdAt": "2026-02-26T11:46:19"}, {"name": "Kandahar", "url": "https://ak.sv/movie/8660/kandahar", "image_url": "https://img.downet.net/thumb/178x260/uploads/DhZsn.jpg", "year": 2023, "genre": "اكشن, اثارة", "rating": 6.0, "createdAt": "2026-02-26T11:46:19"}, {"name": "The Starling Girl", "url": "https://ak.sv/movie/8794/the-starling-girl", "image_url": "https://img.downet.net/thumb/178x260/uploads/fmCIP.jpg", "year": 2023, "genre": "دراما", "rating": 7.2, "createdAt": "2026-02-26T11:46:19"}, {"name": "Trapped in the Farmhouse", "url": "https://ak.sv/movie/8793/trapped-in-the-farmhouse", "image_url": "https://img.downet.net/thumb/178x260/uploads/F75JV.jpg", "year": 2023, "genre": "اثارة", "rating": 5.7, "createdAt": "2026-02-26T11:46:20"}, {"name": "Epic Tails", "url": "https://ak.sv/movie/8792/epic-tails", "image_url": "https://img.downet.net/thumb/178x260/uploads/Z3dW6.jpg", "year": 2023, "genre": "انمي, كوميدي, مغامرة", "rating": 6.0, "createdAt": "2026-02-26T11:46:20"}, {"name": "Colorblind", "url": "https://ak.sv/movie/8791/colorblind", "image_url": "https://img.downet.net/thumb/178x260/uploads/Wkye6.jpg", "year": 2023, "genre": "دراما", "rating": 5.6, "createdAt": "2026-02-26T11:46:20"}, {"name": "Mr. Car and the Knights Templar", "url": "https://ak.sv/movie/8790/mr-car-and-the-knights-templar", "image_url": "https://img.downet.net/thumb/178x260/uploads/F4FsR.jpg", "year": 2023, "genre": "عائلي, دراما, مغامرة", "rating": 5.5, "createdAt": "2026-02-26T11:46:20"}, {"name": "God's Country Song", "url": "https://ak.sv/movie/8789/god-s-country-song", "image_url": "https://img.downet.net/thumb/178x260/uploads/wMVK6.jpg", "year": 2023, "genre": "دراما", "rating": 4.9, "createdAt": "2026-02-26T11:46:20"}, {"name": "Asteroid City", "url": "https://ak.sv/movie/8788/asteroid-city", "image_url": "https://img.downet.net/thumb/178x260/uploads/cp3PA.jpg", "year": 2023, "genre": "كوميدي, رومانسي, دراما", "rating": 7.1, "createdAt": "2026-02-26T11:46:20"}, {"name": "The Roundup: No Way Out", "url": "https://ak.sv/movie/8783/the-roundup-no-way-out", "image_url": "https://img.downet.net/thumb/178x260/uploads/hk4ZQ.jpg", "year": 2023, "genre": "اكشن, اثارة, جريمة", "rating": 6.6, "createdAt": "2026-02-26T11:46:20"}, {"name": "The Out-Laws", "url": "https://ak.sv/movie/8772/the-out-laws", "image_url": "https://img.downet.net/thumb/178x260/uploads/UjBhP.jpg", "year": 2023, "genre": "اكشن, NETFLIX, كوميدي, جريمة", "rating": 6.1, "createdAt": "2026-02-26T11:46:20"}, {"name": "Ghost Town", "url": "https://ak.sv/movie/8787/ghost-town", "image_url": "https://img.downet.net/thumb/178x260/uploads/2XTVI.jpg", "year": 2023, "genre": "اثارة, غربي", "rating": 4.5, "createdAt": "2026-02-26T11:46:20"}, {"name": "LOLA", "url": "https://ak.sv/movie/8786/lola", "image_url": "https://img.downet.net/thumb/178x260/uploads/OhYgl.jpg", "year": 2022, "genre": "حربي, خيال علمي", "rating": 6.7, "createdAt": "2026-02-26T11:46:26"}, {"name": "Cascade", "url": "https://ak.sv/movie/8785/cascade", "image_url": "https://img.downet.net/thumb/178x260/uploads/ay3Qt.jpg", "year": 2023, "genre": "اثارة", "rating": 4.8, "createdAt": "2026-02-26T11:46:26"}, {"name": "Daughter", "url": "https://ak.sv/movie/8784/daughter", "image_url": "https://img.downet.net/thumb/178x260/uploads/BM6fs.jpeg", "year": 2022, "genre": "غموض, دراما", "rating": 6.2, "createdAt": "2026-02-26T11:46:26"}, {"name": "Scream VI", "url": "https://ak.sv/movie/8318/scream-vi-6", "image_url": "https://img.downet.net/thumb/178x260/uploads/aeA57.jpg", "year": 2023, "genre": "اثارة, غموض, رعب", "rating": 6.6, "createdAt": "2026-02-26T11:46:26"}, {"name": "Blind", "url": "https://ak.sv/movie/8781/blind", "image_url": "https://img.downet.net/thumb/178x260/uploads/NeoLQ.jpg", "year": 2023, "genre": "اثارة, دراما, جريمة", "rating": 3.8, "createdAt": "2026-02-26T11:46:26"}, {"name": "Bangkok Storm", "url": "https://ak.sv/movie/8780/bangkok-storm", "image_url": "https://img.downet.net/thumb/178x260/uploads/S5bc1.jpg", "year": 2023, "genre": "اكشن, غموض, جريمة", "rating": 5.5, "createdAt": "2026-02-26T11:46:26"}, {"name": "The Initiated", "url": "https://ak.sv/movie/8779/the-initiated", "image_url": "https://img.downet.net/thumb/178x260/uploads/6GkFl.jpg", "year": 2023, "genre": "اثارة, دراما, جريمة", "rating": 7.2, "createdAt": "2026-02-26T11:46:26"}, {"name": "بيزات", "url": "https://ak.sv/movie/8778/بيزات", "image_url": "https://img.downet.net/thumb/178x260/uploads/oCbo6.jpg", "year": 2023, "genre": "اكشن, كوميدي", "rating": 5.5, "createdAt": "2026-02-26T11:46:26"}, {"name": "Muallim", "url": "https://ak.sv/movie/8777/muallim", "image_url": "https://img.downet.net/thumb/178x260/uploads/4YuyZ.jpg", "year": 2021, "genre": "دراما", "rating": 3.8, "createdAt": "2026-02-26T11:46:26"}, {"name": "Kather Basha Endra Muthuramalingam", "url": "https://ak.sv/movie/8776/kather-basha-endra-muthuramalingam", "image_url": "https://img.downet.net/thumb/178x260/uploads/9XXmB.jpg", "year": 2023, "genre": "اكشن, دراما, جريمة", "rating": 3.3, "createdAt": "2026-02-26T11:46:26"}, {"name": "The Blackening", "url": "https://ak.sv/movie/8775/the-blackening", "image_url": "https://img.downet.net/thumb/178x260/uploads/LmBbC.jpg", "year": 2023, "genre": "كوميدي, اثارة, رعب", "rating": 6.5, "createdAt": "2026-02-26T11:46:26"}, {"name": "Seasons", "url": "https://ak.sv/movie/8771/seasons", "image_url": "https://img.downet.net/thumb/178x260/uploads/guhl1.jpg", "year": 2023, "genre": "NETFLIX, رومانسي, دراما", "rating": 5.5, "createdAt": "2026-02-26T11:46:26"}, {"name": "A Man", "url": "https://ak.sv/movie/8774/a-man", "image_url": "https://img.downet.net/thumb/178x260/uploads/T4WdC.jpg", "year": 2022, "genre": "اثارة, غموض, دراما", "rating": 7.0, "createdAt": "2026-02-26T11:46:26"}, {"name": "IB 71", "url": "https://ak.sv/movie/8773/ib-71", "image_url": "https://img.downet.net/thumb/178x260/uploads/W7qKF.jpg", "year": 2023, "genre": "اكشن, اثارة", "rating": 8.4, "createdAt": "2026-02-26T11:46:26"}, {"name": "Nanmao and Beima", "url": "https://ak.sv/movie/8770/nanmao-and-beima", "image_url": "https://img.downet.net/thumb/178x260/uploads/swwjt.jpg", "year": 2023, "genre": "اثارة, غموض, رعب", "rating": 6.5, "createdAt": "2026-02-26T11:46:26"}, {"name": "Legend of Ghost YingNing", "url": "https://ak.sv/movie/8769/legend-of-ghost-yingning", "image_url": "https://img.downet.net/thumb/178x260/uploads/c0eYv.jpg", "year": 2023, "genre": "رومانسي", "rating": 5.5, "createdAt": "2026-02-26T11:46:26"}, {"name": "كذبة كبيرة", "url": "https://ak.sv/movie/8768/كذبة-كبيرة-5", "image_url": "https://img.downet.net/thumb/178x260/uploads/NAEnl.jpg", "year": 2023, "genre": "كوميدي, دراما", "rating": 5.5, "createdAt": "2026-02-26T11:46:26"}, {"name": "The Wraith Within", "url": "https://ak.sv/movie/8767/the-wraith-within", "image_url": "https://img.downet.net/thumb/178x260/uploads/PI6ff.jpg", "year": 2023, "genre": "اكشن, كوميدي, مغامرة", "rating": 5.4, "createdAt": "2026-02-26T11:46:26"}, {"name": "Chakravyuham: The Trap", "url": "https://ak.sv/movie/8765/chakravyuham-the-trap", "image_url": "https://img.downet.net/thumb/178x260/uploads/HlZUQ.jpg", "year": 2023, "genre": "اثارة, غموض, جريمة", "rating": 8.0, "createdAt": "2026-02-26T11:46:26"}, {"name": "Anni Manchi Sakunamule", "url": "https://ak.sv/movie/8764/anni-manchi-sakunamule-4", "image_url": "https://img.downet.net/thumb/178x260/uploads/bEuQS.jpg", "year": 2023, "genre": "رومانسي, دراما", "rating": 6.2, "createdAt": "2026-02-26T11:46:26"}, {"name": "Warhorse One", "url": "https://ak.sv/movie/8755/warhorse-one", "image_url": "https://img.downet.net/thumb/178x260/uploads/xE8OF.jpg", "year": 2023, "genre": "اكشن, حربي, دراما", "rating": 6.1, "createdAt": "2026-02-26T11:46:26"}, {"name": "All the World Is Sleeping", "url": "https://ak.sv/movie/8766/all-the-world-is-sleeping", "image_url": "https://img.downet.net/thumb/178x260/uploads/NPDHR.jpg", "year": 2023, "genre": "دراما", "rating": 7.3, "createdAt": "2026-02-26T11:46:26"}, {"name": "Gold Brick", "url": "https://ak.sv/movie/8754/gold-brick", "image_url": "https://img.downet.net/thumb/178x260/uploads/yQ6FP.jpg", "year": 2023, "genre": "NETFLIX, كوميدي, دراما", "rating": 5.5, "createdAt": "2026-02-26T11:46:26"}, {"name": "Travel to the East", "url": "https://ak.sv/movie/8763/travel-to-the-east", "image_url": "https://img.downet.net/thumb/178x260/uploads/TjLzt.jpg", "year": 2023, "genre": "اكشن, رومانسي, دراما", "rating": 5.5, "createdAt": "2026-02-26T11:46:26"}, {"name": "The Haunting 3", "url": "https://ak.sv/movie/8762/the-haunting-3", "image_url": "https://img.downet.net/thumb/178x260/uploads/i4ZHo.jpg", "year": 2023, "genre": "اثارة, غموض, رعب", "rating": 7.6, "createdAt": "2026-02-26T11:46:26"}, {"name": "Qinling Town Tiancoffins", "url": "https://ak.sv/movie/8760/qinling-town-tiancoffins", "image_url": "https://img.downet.net/thumb/178x260/uploads/bFj5n.jpg", "year": 2023, "genre": "اثارة, غموض, مغامرة", "rating": 6.5, "createdAt": "2026-02-26T11:46:27"}, {"name": "Night of soul returning", "url": "https://ak.sv/movie/8759/night-of-soul-returning", "image_url": "https://img.downet.net/thumb/178x260/uploads/KXLg7.jpg", "year": 2023, "genre": "اثارة, غموض", "rating": 6.5, "createdAt": "2026-02-26T11:46:27"}, {"name": "Big eudemon", "url": "https://ak.sv/movie/8758/big-eudemon", "image_url": "https://img.downet.net/thumb/178x260/uploads/ST4QG.jpg", "year": 2023, "genre": "اكشن, فانتازيا", "rating": 5.5, "createdAt": "2026-02-26T11:46:27"}, {"name": "Beast in River", "url": "https://ak.sv/movie/8756/beast-in-river", "image_url": "https://img.downet.net/thumb/178x260/uploads/ehOBx.jpg", "year": 2023, "genre": "فانتازيا, رعب", "rating": 5.5, "createdAt": "2026-02-26T11:46:27"}, {"name": "Beau Is Afraid", "url": "https://ak.sv/movie/8641/beau-is-afraid-3", "image_url": "https://img.downet.net/thumb/178x260/uploads/rJdmg.jpg", "year": 2023, "genre": "كوميدي, دراما, رعب", "rating": 6.9, "createdAt": "2026-02-26T11:46:27"}, {"name": "Assassin", "url": "https://ak.sv/movie/8264/assassin", "image_url": "https://img.downet.net/thumb/178x260/uploads/kahvJ.jpg", "year": 2023, "genre": "اكشن, اثارة, جريمة", "rating": 3.1, "createdAt": "2026-02-26T11:46:32"}, {"name": "Kulasami", "url": "https://ak.sv/movie/8752/kulasami", "image_url": "https://img.downet.net/thumb/178x260/uploads/NlOAd.jpg", "year": 2023, "genre": "اكشن, اثارة, دراما", "rating": 5.6, "createdAt": "2026-02-26T11:46:32"}, {"name": "Alabama Rose", "url": "https://ak.sv/movie/8751/alabama-rose", "image_url": "https://img.downet.net/thumb/178x260/uploads/JgfWN.jpg", "year": 2022, "genre": "اثارة", "rating": 5.0, "createdAt": "2026-02-26T11:46:32"}, {"name": "Prisoner's Daughter", "url": "https://ak.sv/movie/8750/prisoner-s-daughter", "image_url": "https://img.downet.net/thumb/178x260/uploads/cWpR2.jpg", "year": 2022, "genre": "دراما", "rating": 6.3, "createdAt": "2026-02-26T11:46:32"}, {"name": "The Redeemer", "url": "https://ak.sv/movie/8749/the-redeemer", "image_url": "https://img.downet.net/thumb/178x260/uploads/p6ijg.jpg", "year": 2023, "genre": "غربي", "rating": 5.5, "createdAt": "2026-02-26T11:46:32"}, {"name": "Medusa's Venom", "url": "https://ak.sv/movie/8748/medusa-s-venom", "image_url": "https://img.downet.net/thumb/178x260/uploads/1SgMS.jpg", "year": 2023, "genre": "رعب", "rating": 4.8, "createdAt": "2026-02-26T11:46:33"}, {"name": "Eye for Eye", "url": "https://ak.sv/movie/8747/eye-for-eye", "image_url": "https://img.downet.net/thumb/178x260/uploads/Oaqgv.jpg", "year": 2022, "genre": "غربي", "rating": 4.2, "createdAt": "2026-02-26T11:46:33"}, {"name": "Small, Slow But Steady", "url": "https://ak.sv/movie/8746/small-slow-but-steady", "image_url": "https://img.downet.net/thumb/178x260/uploads/Vv5zK.jpg", "year": 2022, "genre": "رياضي, دراما", "rating": 7.0, "createdAt": "2026-02-26T11:46:33"}, {"name": "The Glorious my Revenge", "url": "https://ak.sv/movie/8745/the-glorious-my-revenge", "image_url": "https://img.downet.net/thumb/178x260/uploads/bYWSK.jpg", "year": 2023, "genre": "دراما", "rating": 4.6, "createdAt": "2026-02-26T11:46:33"}, {"name": "Signs of Love", "url": "https://ak.sv/movie/8744/signs-of-love", "image_url": "https://img.downet.net/thumb/178x260/uploads/Crv5A.jpg", "year": 2022, "genre": "رومانسي, دراما", "rating": 5.6, "createdAt": "2026-02-26T11:46:33"}, {"name": "Little Bone Lodge", "url": "https://ak.sv/movie/8741/little-bone-lodge-5", "image_url": "https://img.downet.net/thumb/178x260/uploads/cOCNd.jpg", "year": 2023, "genre": "اثارة, رعب, جريمة", "rating": 6.4, "createdAt": "2026-02-26T11:46:33"}, {"name": "Sins of the Preacher's Wife", "url": "https://ak.sv/movie/8743/sins-of-the-preacher-s-wife", "image_url": "https://img.downet.net/thumb/178x260/uploads/eYzHQ.jpg", "year": 2023, "genre": "اثارة", "rating": 5.6, "createdAt": "2026-02-26T11:46:33"}, {"name": "Gabriel's Redemption: Part One", "url": "https://ak.sv/movie/8742/gabriel-s-redemption-part-one", "image_url": "https://img.downet.net/thumb/178x260/uploads/FcuAt.jpg", "year": 2023, "genre": "رومانسي", "rating": 4.8, "createdAt": "2026-02-26T11:46:33"}, {"name": "The Human Centipede III", "url": "https://ak.sv/movie/8735/the-human-centipede-iii", "image_url": "https://img.downet.net/thumb/178x260/uploads/adf7Z.jpg", "year": 2015, "genre": "كوميدي, رعب", "rating": 2.8, "createdAt": "2026-02-26T11:46:33"}, {"name": "The Human Centipede II", "url": "https://ak.sv/movie/8734/the-human-centipede-ii", "image_url": "https://img.downet.net/thumb/178x260/uploads/1dg6v.jpg", "year": 2011, "genre": "رعب", "rating": 3.8, "createdAt": "2026-02-26T11:46:33"}, {"name": "The Human Centipede", "url": "https://ak.sv/movie/8733/the-human-centipede", "image_url": "https://img.downet.net/thumb/178x260/uploads/OuK1a.jpg", "year": 2009, "genre": "رعب", "rating": 4.4, "createdAt": "2026-02-26T11:46:33"}, {"name": "Soundproof", "url": "https://ak.sv/movie/8740/soundproof", "image_url": "https://img.downet.net/thumb/178x260/uploads/ZtNul.jpg", "year": 2023, "genre": "دراما, جريمة", "rating": 6.5, "createdAt": "2026-02-26T11:46:33"}, {"name": "Sisu", "url": "https://ak.sv/movie/8402/sisu-1", "image_url": "https://img.downet.net/thumb/178x260/uploads/SpMms.jpg", "year": 2023, "genre": "اكشن, حربي", "rating": 6.9, "createdAt": "2026-02-26T11:46:33"}, {"name": "عنتر بن شداد", "url": "https://ak.sv/movie/8732/عنتر-بن-شداد", "image_url": "https://img.downet.net/thumb/178x260/uploads/cc0Tk.jpg", "year": 1961, "genre": "اثارة, سيرة ذاتية, رومانسي, دراما", "rating": 7.2, "createdAt": "2026-02-26T11:46:33"}, {"name": "The Martian", "url": "https://ak.sv/movie/8731/the-martian", "image_url": "https://img.downet.net/thumb/178x260/uploads/nSIhD.jpg", "year": 2015, "genre": "خيال علمي, دراما, مغامرة", "rating": 8.0, "createdAt": "2026-02-26T11:46:33"}, {"name": "Speed 2: Cruise Control", "url": "https://ak.sv/movie/8729/speed-2-cruise-control", "image_url": "https://img.downet.net/thumb/178x260/uploads/nkQeu.jpg", "year": 1997, "genre": "اكشن, جريمة, مغامرة", "rating": 3.9, "createdAt": "2026-02-26T11:46:33"}, {"name": "Speed", "url": "https://ak.sv/movie/8730/speed", "image_url": "https://img.downet.net/thumb/178x260/uploads/U9KxC.jpg", "year": 1994, "genre": "اكشن, اثارة, مغامرة", "rating": 7.3, "createdAt": "2026-02-26T11:46:33"}, {"name": "End of Days", "url": "https://ak.sv/movie/8728/end-of-days", "image_url": "https://img.downet.net/thumb/178x260/uploads/Bj77G.jpg", "year": 1999, "genre": "اكشن, فانتازيا, رعب", "rating": 5.8, "createdAt": "2026-02-26T11:46:33"}, {"name": "ساحر النساء", "url": "https://ak.sv/movie/8738/ساحر-النساء", "image_url": "https://img.downet.net/thumb/178x260/uploads/vzDN3.jpg", "year": 2023, "genre": "غموض", "rating": 5.1, "createdAt": "2026-02-26T11:46:33"}, {"name": "Angry Neighbors", "url": "https://ak.sv/movie/8739/angry-neighbors-3", "image_url": "https://img.downet.net/thumb/178x260/uploads/QGzcf.jpg", "year": 2022, "genre": "كوميدي", "rating": 4.1, "createdAt": "2026-02-26T11:46:33"}, {"name": "Hunt Club", "url": "https://ak.sv/movie/8737/hunt-club", "image_url": "https://img.downet.net/thumb/178x260/uploads/UVeJr.jpg", "year": 2023, "genre": "اكشن, اثارة", "rating": 4.5, "createdAt": "2026-02-26T11:46:33"}, {"name": "Veeran", "url": "https://ak.sv/movie/8727/veeran", "image_url": "https://img.downet.net/thumb/178x260/uploads/Sluom.jpg", "year": 2023, "genre": "اكشن, فانتازيا, دراما", "rating": 6.5, "createdAt": "2026-02-26T11:46:33"}, {"name": "Lakadbaggha", "url": "https://ak.sv/movie/8726/lakadbaggha", "image_url": "https://img.downet.net/thumb/178x260/uploads/kGiEO.jpg", "year": 2023, "genre": "اكشن, كوميدي, جريمة", "rating": 6.4, "createdAt": "2026-02-26T11:46:33"}, {"name": "Sergeant", "url": "https://ak.sv/movie/8725/sergeant", "image_url": "https://img.downet.net/thumb/178x260/uploads/wmjV4.jpg", "year": 2023, "genre": "اثارة, دراما", "rating": 4.9, "createdAt": "2026-02-26T11:46:33"}, {"name": "The Ones You Didn't Burn", "url": "https://ak.sv/movie/8724/the-ones-you-didn-t-burn", "image_url": "https://img.downet.net/thumb/178x260/uploads/7ux05.jpg", "year": 2022, "genre": "رعب", "rating": 6.4, "createdAt": "2026-02-26T11:46:33"}, {"name": "Lust Stories 2", "url": "https://ak.sv/movie/8723/lust-stories-2", "image_url": "https://img.downet.net/thumb/178x260/uploads/wIArr.jpg", "year": 2023, "genre": "NETFLIX, رومانسي, دراما", "rating": 7.3, "createdAt": "2026-02-26T11:46:38"}, {"name": "Afwaah", "url": "https://ak.sv/movie/8722/afwaah", "image_url": "https://img.downet.net/thumb/178x260/uploads/frjMA.jpg", "year": 2023, "genre": "اثارة, دراما", "rating": 5.3, "createdAt": "2026-02-26T11:46:38"}, {"name": "Mavka. Lisova pisnya", "url": "https://ak.sv/movie/8721/mavka-lisova-pisnya", "image_url": "https://img.downet.net/thumb/178x260/uploads/zQyzB.jpg", "year": 2023, "genre": "انمي, كوميدي, مغامرة", "rating": 7.6, "createdAt": "2026-02-26T11:46:38"}, {"name": "You Hurt My Feelings", "url": "https://ak.sv/movie/8719/you-hurt-my-feelings-3", "image_url": "https://img.downet.net/thumb/178x260/uploads/xJXiO.jpg", "year": 2023, "genre": "كوميدي, دراما", "rating": 6.9, "createdAt": "2026-02-26T11:46:39"}, {"name": "نيمونا", "url": "https://ak.sv/movie/8718/نيمونا", "image_url": "https://img.downet.net/thumb/178x260/uploads/9Kh4P.jpg", "year": 2023, "genre": "انمي, اكشن, NETFLIX, مغامرة", "rating": 7.5, "createdAt": "2026-02-26T11:46:39"}, {"name": "Nimona", "url": "https://ak.sv/movie/8717/nimona", "image_url": "https://img.downet.net/thumb/178x260/uploads/u1R3K.jpg", "year": 2023, "genre": "انمي, اكشن, NETFLIX, مغامرة", "rating": 7.5, "createdAt": "2026-02-26T11:46:39"}, {"name": "She Inherited Danger", "url": "https://ak.sv/movie/8716/she-inherited-danger", "image_url": "https://img.downet.net/thumb/178x260/uploads/kvcgk.jpg", "year": 2023, "genre": "اثارة", "rating": 6.1, "createdAt": "2026-02-26T11:46:39"}, {"name": "Kazhuvethi Moorkkan", "url": "https://ak.sv/movie/8715/kazhuvethi-moorkkan", "image_url": "https://img.downet.net/thumb/178x260/uploads/IqqCp.jpg", "year": 2023, "genre": "اكشن, كوميدي, دراما", "rating": 6.2, "createdAt": "2026-02-26T11:46:39"}, {"name": "Run Rabbit Run", "url": "https://ak.sv/movie/8713/run-rabbit-run", "image_url": "https://img.downet.net/thumb/178x260/uploads/WAtpa.jpg", "year": 2023, "genre": "اثارة, رعب", "rating": 5.2, "createdAt": "2026-02-26T11:46:39"}, {"name": "Seire", "url": "https://ak.sv/movie/8714/seire", "image_url": "https://img.downet.net/thumb/178x260/uploads/WkqhE.jpg", "year": 2022, "genre": "دراما, رعب", "rating": 5.9, "createdAt": "2026-02-26T11:46:39"}, {"name": "ساعة إجابة", "url": "https://ak.sv/movie/8706/ساعة-إجابة-5", "image_url": "https://img.downet.net/thumb/178x260/uploads/LmGi6.jpg", "year": 2023, "genre": "كوميدي, عائلي, خيال علمي", "rating": 4.9, "createdAt": "2026-02-26T11:46:39"}, {"name": "Extraction 2", "url": "https://ak.sv/movie/8662/extraction-2", "image_url": "https://img.downet.net/thumb/178x260/uploads/kgqLc.jpg", "year": 2023, "genre": "اكشن, NETFLIX, اثارة", "rating": 8.5, "createdAt": "2026-02-26T11:46:39"}, {"name": "كيرة والجن", "url": "https://ak.sv/movie/6721/كيرة-والجن", "image_url": "https://img.downet.net/thumb/178x260/uploads/5iUVY.jpg", "year": 2022, "genre": "اكشن, اثارة, تاريخي, دراما", "rating": 8.1, "createdAt": "2026-02-26T11:46:39"}, {"name": "هارلي", "url": "https://ak.sv/movie/8358/هارلي-1", "image_url": "https://img.downet.net/thumb/178x260/uploads/X9HGz.jpg", "year": 2023, "genre": "اكشن", "rating": 4.4, "createdAt": "2026-02-26T11:46:39"}, {"name": "Resurrected", "url": "https://ak.sv/movie/8711/resurrected", "image_url": "https://img.downet.net/thumb/178x260/uploads/2wwBN.jpg", "year": 2023, "genre": "خيال علمي, رعب", "rating": 4.9, "createdAt": "2026-02-26T11:46:39"}, {"name": "The Swearing Jar", "url": "https://ak.sv/movie/8709/the-swearing-jar", "image_url": "https://img.downet.net/thumb/178x260/uploads/7pohR.jpg", "year": 2022, "genre": "موسيقى, رومانسي, دراما", "rating": 6.2, "createdAt": "2026-02-26T11:46:39"}, {"name": "Summer at Charlotte's", "url": "https://ak.sv/movie/8708/summer-at-charlotte-s", "image_url": "https://img.downet.net/thumb/178x260/uploads/0pWth.jpg", "year": 2023, "genre": "رومانسي", "rating": 5.5, "createdAt": "2026-02-26T11:46:39"}, {"name": "Sheroes", "url": "https://ak.sv/movie/8707/sheroes", "image_url": "https://img.downet.net/thumb/178x260/uploads/dmBKj.jpg", "year": 2023, "genre": "اكشن, مغامرة", "rating": 3.1, "createdAt": "2026-02-26T11:46:39"}, {"name": "The Stand In", "url": "https://ak.sv/movie/8712/the-stand-in", "image_url": "https://img.downet.net/thumb/178x260/uploads/rAesB.jpg", "year": 2020, "genre": "كوميدي, دراما", "rating": 4.7, "createdAt": "2026-02-26T11:46:39"}, {"name": "Evil Dead Rise", "url": "https://ak.sv/movie/8349/evil-dead-rise-1", "image_url": "https://img.downet.net/thumb/178x260/uploads/xOWnx.jpg", "year": 2023, "genre": "رعب", "rating": 6.7, "createdAt": "2026-02-26T11:46:39"}, {"name": "World's Best", "url": "https://ak.sv/movie/8704/world-s-best", "image_url": "https://img.downet.net/thumb/178x260/uploads/oqQZ0.jpg", "year": 2023, "genre": "كوميدي, عائلي, موسيقى", "rating": 6.0, "createdAt": "2026-02-26T11:46:39"}, {"name": "Karungaapiyam", "url": "https://ak.sv/movie/8703/karungaapiyam", "image_url": "https://img.downet.net/thumb/178x260/uploads/IhCgs.jpg", "year": 2023, "genre": "اثارة, رعب", "rating": 7.8, "createdAt": "2026-02-26T11:46:39"}, {"name": "Kisi Ka Bhai Kisi Ki Jaan", "url": "https://ak.sv/movie/8701/kisi-ka-bhai-kisi-ki-jaan", "image_url": "https://img.downet.net/thumb/178x260/uploads/gxcP6.jpg", "year": 2023, "genre": "اكشن, كوميدي, دراما", "rating": 6.7, "createdAt": "2026-02-26T11:46:39"}, {"name": "iNumber Number: Jozi Gold", "url": "https://ak.sv/movie/8698/inumber-number-jozi-gold", "image_url": "https://img.downet.net/thumb/178x260/uploads/TlBQg.jpg", "year": 2023, "genre": "اكشن, NETFLIX, جريمة, مغامرة", "rating": 3.7, "createdAt": "2026-02-26T11:46:39"}, {"name": "اجعلني أصدق", "url": "https://ak.sv/movie/8697/اجعلني-أصدق", "image_url": "https://img.downet.net/thumb/178x260/uploads/bnmWX.jpg", "year": 2023, "genre": "مدبلج, NETFLIX, رومانسي", "rating": 8.0, "createdAt": "2026-02-26T11:46:39"}, {"name": "Make Me Believe", "url": "https://ak.sv/movie/8696/make-me-believe", "image_url": "https://img.downet.net/thumb/178x260/uploads/5LW8a.jpg", "year": 2023, "genre": "رومانسي, NETFLIX", "rating": 8.0, "createdAt": "2026-02-26T11:46:39"}, {"name": "The Perfect Find", "url": "https://ak.sv/movie/8695/the-perfect-find", "image_url": "https://img.downet.net/thumb/178x260/uploads/ZnOey.jpg", "year": 2023, "genre": "NETFLIX, كوميدي, رومانسي, دراما", "rating": 7.4, "createdAt": "2026-02-26T11:46:39"}, {"name": "Through My Window: Across the Sea", "url": "https://ak.sv/movie/8694/through-my-window-across-the-sea", "image_url": "https://img.downet.net/thumb/178x260/uploads/zKQ7g.jpg", "year": 2023, "genre": "NETFLIX, كوميدي, رومانسي, دراما", "rating": 8.8, "createdAt": "2026-02-26T11:46:39"}, {"name": "An Unforgettable Year Spring", "url": "https://ak.sv/movie/8693/an-unforgettable-year-spring", "image_url": "https://img.downet.net/thumb/178x260/uploads/FKsX1.jpg", "year": 2023, "genre": "رومانسي, دراما", "rating": 5.5, "createdAt": "2026-02-26T11:46:39"}, {"name": "King of Clones", "url": "https://ak.sv/movie/8699/king-of-clones", "image_url": "https://img.downet.net/thumb/178x260/uploads/L6dzW.jpg", "year": 2023, "genre": "وثائقي, NETFLIX", "rating": 5.5, "createdAt": "2026-02-26T11:46:39"}, {"name": "The Machine", "url": "https://ak.sv/movie/8692/the-machine", "image_url": "https://img.downet.net/thumb/178x260/uploads/fBnjc.jpg", "year": 2023, "genre": "اكشن, كوميدي", "rating": 6.2, "createdAt": "2026-02-26T11:46:45"}, {"name": "Sanctuary", "url": "https://ak.sv/movie/8690/sanctuary", "image_url": "https://img.downet.net/thumb/178x260/uploads/wkgSV.jpg", "year": 2022, "genre": "اثارة, دراما", "rating": 6.9, "createdAt": "2026-02-26T11:46:45"}, {"name": "Game of Death", "url": "https://ak.sv/movie/8638/game-of-death", "image_url": "https://img.downet.net/thumb/178x260/uploads/xqrk0.jpg", "year": 1978, "genre": "اكشن, دراما, جريمة", "rating": 5.9, "createdAt": "2026-02-26T11:46:45"}, {"name": "Enter the Dragon", "url": "https://ak.sv/movie/8633/enter-the-dragon", "image_url": "https://img.downet.net/thumb/178x260/uploads/TCw25.jpg", "year": 1973, "genre": "اكشن, دراما, جريمة", "rating": 7.6, "createdAt": "2026-02-26T11:46:45"}, {"name": "The Way Of The Dragon", "url": "https://ak.sv/movie/8653/the-way-of-the-dragon", "image_url": "https://img.downet.net/thumb/178x260/uploads/bEQmY.jpg", "year": 1972, "genre": "اكشن, كوميدي, مغامرة", "rating": 7.2, "createdAt": "2026-02-26T11:46:45"}, {"name": "Fist of Fury", "url": "https://ak.sv/movie/8636/fist-of-fury", "image_url": "https://img.downet.net/thumb/178x260/uploads/d1F88.jpg", "year": 1972, "genre": "اكشن, رومانسي, دراما", "rating": 7.2, "createdAt": "2026-02-26T11:46:45"}, {"name": "The Big Boss", "url": "https://ak.sv/movie/8650/the-big-boss", "image_url": "https://img.downet.net/thumb/178x260/uploads/sZyTT.jpg", "year": 1971, "genre": "اكشن, دراما, جريمة", "rating": 6.9, "createdAt": "2026-02-26T11:46:45"}, {"name": "The Sea Monster", "url": "https://ak.sv/movie/8689/the-sea-monster", "image_url": "https://img.downet.net/thumb/178x260/uploads/X6Zns.jpg", "year": 2023, "genre": "اكشن, مغامرة", "rating": 6.5, "createdAt": "2026-02-26T11:46:45"}, {"name": "Miracle Fighters", "url": "https://ak.sv/movie/8688/miracle-fighters", "image_url": "https://img.downet.net/thumb/178x260/uploads/txsZX.jpg", "year": 2023, "genre": "اكشن, فانتازيا", "rating": 5.5, "createdAt": "2026-02-26T11:46:45"}, {"name": "Dominion: Prequel to the Exorcist", "url": "https://ak.sv/movie/8632/dominion-prequel-to-the-exorcist", "image_url": "https://img.downet.net/thumb/178x260/uploads/3C2ME.jpg", "year": 2005, "genre": "اثارة, دراما, رعب", "rating": 5.2, "createdAt": "2026-02-26T11:46:45"}, {"name": "Exorcist: The Beginning", "url": "https://ak.sv/movie/8635/exorcist-the-beginning", "image_url": "https://img.downet.net/thumb/178x260/uploads/QlzgV.jpg", "year": 2004, "genre": "اثارة, غموض, رعب", "rating": 5.1, "createdAt": "2026-02-26T11:46:45"}, {"name": "The Exorcist III", "url": "https://ak.sv/movie/8647/the-exorcist-iii", "image_url": "https://img.downet.net/thumb/178x260/uploads/wX8Ws.jpg", "year": 1990, "genre": "اثارة, غموض, رعب", "rating": 6.5, "createdAt": "2026-02-26T11:46:45"}, {"name": "Exorcist II: The Heretic", "url": "https://ak.sv/movie/8634/exorcist-ii-the-heretic", "image_url": "https://img.downet.net/thumb/178x260/uploads/xFqAr.jpg", "year": 1977, "genre": "رعب", "rating": 3.8, "createdAt": "2026-02-26T11:46:46"}, {"name": "The Exorcist", "url": "https://ak.sv/movie/8646/the-exorcist", "image_url": "https://img.downet.net/thumb/178x260/uploads/vRNIl.jpg", "year": 1973, "genre": "رعب", "rating": 8.1, "createdAt": "2026-02-26T11:46:46"}, {"name": "Coyote", "url": "https://ak.sv/movie/8686/coyote", "image_url": "https://img.downet.net/thumb/178x260/uploads/zPYXY.jpg", "year": 2023, "genre": "خيال علمي", "rating": 7.0, "createdAt": "2026-02-26T11:46:46"}, {"name": "Honest Candidate 2", "url": "https://ak.sv/movie/8687/honest-candidate-2", "image_url": "https://img.downet.net/thumb/178x260/uploads/XjmCY.jpg", "year": 2022, "genre": "كوميدي", "rating": 5.2, "createdAt": "2026-02-26T11:46:46"}, {"name": "I Like Movies", "url": "https://ak.sv/movie/8685/i-like-movies", "image_url": "https://img.downet.net/thumb/178x260/uploads/5n9GB.jpg", "year": 2022, "genre": "كوميدي", "rating": 6.8, "createdAt": "2026-02-26T11:46:46"}, {"name": "World War Z", "url": "https://ak.sv/movie/8663/world-war-z-8", "image_url": "https://img.downet.net/thumb/178x260/uploads/cObR3.jpg", "year": 2013, "genre": "اكشن, رعب, مغامرة", "rating": 7.0, "createdAt": "2026-02-26T11:46:46"}, {"name": "The Wall", "url": "https://ak.sv/movie/8649/the-wall", "image_url": "https://img.downet.net/thumb/178x260/uploads/p8IiT.jpg", "year": 2017, "genre": "اكشن, اثارة, دراما", "rating": 6.2, "createdAt": "2026-02-26T11:46:46"}, {"name": "The Man from U.N.C.L.E", "url": "https://ak.sv/movie/8652/the-man-from-u-n-c-l-e", "image_url": "https://img.downet.net/thumb/178x260/uploads/hXdIj.jpg", "year": 2015, "genre": "اكشن, كوميدي, مغامرة", "rating": 7.2, "createdAt": "2026-02-26T11:46:46"}, {"name": "The Forbidden Kingdom", "url": "https://ak.sv/movie/8651/the-forbidden-kingdom", "image_url": "https://img.downet.net/thumb/178x260/uploads/tuMIO.jpg", "year": 2008, "genre": "اكشن, فانتازيا, مغامرة", "rating": 6.5, "createdAt": "2026-02-26T11:46:46"}, {"name": "Into the Blue 2: The Reef", "url": "https://ak.sv/movie/8644/into-the-blue-2-the-reef", "image_url": "https://img.downet.net/thumb/178x260/uploads/EgDkK.jpg", "year": 2009, "genre": "اكشن, اثارة, مغامرة", "rating": 4.7, "createdAt": "2026-02-26T11:46:46"}, {"name": "Into the Blue", "url": "https://ak.sv/movie/8643/into-the-blue", "image_url": "https://img.downet.net/thumb/178x260/uploads/8GFs7.jpg", "year": 2005, "genre": "اكشن, جريمة, مغامرة", "rating": 5.9, "createdAt": "2026-02-26T11:46:46"}, {"name": "Pichaikkaran 2", "url": "https://ak.sv/movie/8684/pichaikkaran-2", "image_url": "https://img.downet.net/thumb/178x260/uploads/pElMJ.jpg", "year": 2023, "genre": "اكشن, خيال علمي, دراما", "rating": 6.0, "createdAt": "2026-02-26T11:46:46"}, {"name": "Siya", "url": "https://ak.sv/movie/8683/siya", "image_url": "https://img.downet.net/thumb/178x260/uploads/LVRt9.jpg", "year": 2022, "genre": "دراما, جريمة", "rating": 8.9, "createdAt": "2026-02-26T11:46:46"}, {"name": "An Unforgettable Year: Summer", "url": "https://ak.sv/movie/8682/an-unforgettable-year-summer", "image_url": "https://img.downet.net/thumb/178x260/uploads/syGph.jpg", "year": 2023, "genre": "دراما, غربي", "rating": 5.4, "createdAt": "2026-02-26T11:46:46"}, {"name": "Son of Saul", "url": "https://ak.sv/movie/8645/son-of-saul", "image_url": "https://img.downet.net/thumb/178x260/uploads/9gPdv.jpg", "year": 2015, "genre": "حربي, دراما", "rating": 7.4, "createdAt": "2026-02-26T11:46:46"}, {"name": "Passengers", "url": "https://ak.sv/movie/8664/passengers", "image_url": "https://img.downet.net/thumb/178x260/uploads/GBThF.jpg", "year": 2016, "genre": "خيال علمي, رومانسي, دراما", "rating": 7.0, "createdAt": "2026-02-26T11:46:46"}, {"name": "I Saw the Devil", "url": "https://ak.sv/movie/8642/i-saw-the-devil", "image_url": "https://img.downet.net/thumb/178x260/uploads/oJwUz.jpg", "year": 2010, "genre": "اكشن, رعب, جريمة", "rating": 7.8, "createdAt": "2026-02-26T11:46:46"}, {"name": "Friends with Benefits", "url": "https://ak.sv/movie/8637/friends-with-benefits", "image_url": "https://img.downet.net/thumb/178x260/uploads/ThmXs.jpg", "year": 2011, "genre": "كوميدي, رومانسي", "rating": 6.5, "createdAt": "2026-02-26T11:46:46"}, {"name": "A Prophet", "url": "https://ak.sv/movie/8631/a-prophet", "image_url": "https://img.downet.net/thumb/178x260/uploads/ydAJ7.jpg", "year": 2009, "genre": "دراما, جريمة", "rating": 7.8, "createdAt": "2026-02-26T11:46:51"}, {"name": "Darkest Hour Annihilation", "url": "https://ak.sv/movie/8681/darkest-hour-annihilation", "image_url": "https://img.downet.net/thumb/178x260/uploads/N0udP.jpg", "year": 2022, "genre": "اثارة, غموض, دراما", "rating": 7.0, "createdAt": "2026-02-26T11:46:51"}, {"name": "The First Day of my Life", "url": "https://ak.sv/movie/8680/the-first-day-of-my-life", "image_url": "https://img.downet.net/thumb/178x260/uploads/3gYAP.jpg", "year": 2023, "genre": "كوميدي, فانتازيا, دراما", "rating": 6.6, "createdAt": "2026-02-26T11:46:51"}, {"name": "Pocket Dial Murder", "url": "https://ak.sv/movie/8679/pocket-dial-murder", "image_url": "https://img.downet.net/thumb/178x260/uploads/B53DC.jpg", "year": 2023, "genre": "اثارة", "rating": 5.8, "createdAt": "2026-02-26T11:46:51"}, {"name": "Hi-Fear", "url": "https://ak.sv/movie/8678/hi-fear", "image_url": "https://img.downet.net/thumb/178x260/uploads/xkFIS.jpg", "year": 2022, "genre": "رعب", "rating": 5.2, "createdAt": "2026-02-26T11:46:51"}, {"name": "Cannibal Cabin", "url": "https://ak.sv/movie/8677/cannibal-cabin-2", "image_url": "https://img.downet.net/thumb/178x260/uploads/5TRjM.jpg", "year": 2022, "genre": "رعب", "rating": 2.5, "createdAt": "2026-02-26T11:46:51"}, {"name": "Tamilarasan", "url": "https://ak.sv/movie/8676/tamilarasan", "image_url": "https://img.downet.net/thumb/178x260/uploads/hUq0d.jpg", "year": 2023, "genre": "اكشن, اثارة, دراما", "rating": 6.4, "createdAt": "2026-02-26T11:46:51"}, {"name": "Raavana Kottam", "url": "https://ak.sv/movie/8675/raavana-kottam", "image_url": "https://img.downet.net/thumb/178x260/uploads/xijm5.jpg", "year": 2023, "genre": "اكشن, دراما", "rating": 7.9, "createdAt": "2026-02-26T11:46:51"}, {"name": "The Man from Toronto", "url": "https://ak.sv/movie/6629/the-man-from-toronto", "image_url": "https://img.downet.net/thumb/178x260/uploads/dnmj9.jpg", "year": 2022, "genre": "اكشن, NETFLIX, كوميدي, اثارة", "rating": 5.8, "createdAt": "2026-02-26T11:46:51"}, {"name": "Renfield", "url": "https://ak.sv/movie/8341/renfield", "image_url": "https://img.downet.net/thumb/178x260/uploads/6pQ1S.jpg", "year": 2023, "genre": "كوميدي, فانتازيا, رعب", "rating": 6.4, "createdAt": "2026-02-26T11:46:51"}, {"name": "Polite Society", "url": "https://ak.sv/movie/8470/polite-society", "image_url": "https://img.downet.net/thumb/178x260/uploads/kNdWn.jpg", "year": 2023, "genre": "اكشن, كوميدي", "rating": 6.7, "createdAt": "2026-02-26T11:46:52"}, {"name": "The Covenant", "url": "https://ak.sv/movie/8395/the-covenant-1", "image_url": "https://img.downet.net/thumb/178x260/uploads/ObVU1.jpg", "year": 2023, "genre": "اكشن, اثارة", "rating": 7.5, "createdAt": "2026-02-26T11:46:52"}, {"name": "Maggie Moore(s)", "url": "https://ak.sv/movie/8674/maggie-moores", "image_url": "https://img.downet.net/thumb/178x260/uploads/566Wh.jpg", "year": 2023, "genre": "كوميدي, اثارة, جريمة", "rating": 6.1, "createdAt": "2026-02-26T11:46:52"}, {"name": "The Wrath of Becky", "url": "https://ak.sv/movie/8673/the-wrath-of-becky", "image_url": "https://img.downet.net/thumb/178x260/uploads/AKLoR.jpg", "year": 2023, "genre": "اكشن, اثارة, رعب", "rating": 6.3, "createdAt": "2026-02-26T11:46:52"}, {"name": "Zindagi Shatranj Hai", "url": "https://ak.sv/movie/8672/zindagi-shatranj-hai", "image_url": "https://img.downet.net/thumb/178x260/uploads/qKuVN.jpg", "year": 2023, "genre": "اثارة", "rating": 6.2, "createdAt": "2026-02-26T11:46:52"}, {"name": "Legend of Alkaid", "url": "https://ak.sv/movie/8671/legend-of-alkaid", "image_url": "https://img.downet.net/thumb/178x260/uploads/POgel.jpg", "year": 2023, "genre": "اكشن, غموض, خيال علمي", "rating": 6.0, "createdAt": "2026-02-26T11:46:52"}, {"name": "Yin-Yang Cross-border Person", "url": "https://ak.sv/movie/8670/yin-yang-cross-border-person", "image_url": "https://img.downet.net/thumb/178x260/uploads/5UizJ.jpg", "year": 2023, "genre": "فانتازيا, رعب", "rating": 5.5, "createdAt": "2026-02-26T11:46:52"}, {"name": "The Village", "url": "https://ak.sv/movie/8669/the-village", "image_url": "https://img.downet.net/thumb/178x260/uploads/9m3nz.jpg", "year": 2023, "genre": "دراما", "rating": 6.6, "createdAt": "2026-02-26T11:46:52"}, {"name": "On Sacred Ground", "url": "https://ak.sv/movie/8668/on-sacred-ground", "image_url": "https://img.downet.net/thumb/178x260/uploads/5AFk5.jpg", "year": 2023, "genre": "دراما", "rating": 6.0, "createdAt": "2026-02-26T11:46:52"}, {"name": "Black Clover: Sword of the Wizard King", "url": "https://ak.sv/movie/8667/black-clover-sword-of-the-wizard-king", "image_url": "https://img.downet.net/thumb/178x260/uploads/nltSb.jpg", "year": 2023, "genre": "انمي, اكشن, NETFLIX, مغامرة", "rating": 8.5, "createdAt": "2026-02-26T11:46:52"}, {"name": "Chevalier", "url": "https://ak.sv/movie/8665/chevalier", "image_url": "https://img.downet.net/thumb/178x260/uploads/SWh4r.jpg", "year": 2022, "genre": "سيرة ذاتية, تاريخي, دراما", "rating": 6.8, "createdAt": "2026-02-26T11:46:52"}, {"name": "Pinball: The Man Who Saved the Game", "url": "https://ak.sv/movie/8661/pinball-the-man-who-saved-the-game", "image_url": "https://img.downet.net/thumb/178x260/uploads/MJS3t.jpg", "year": 2022, "genre": "كوميدي, سيرة ذاتية, دراما", "rating": 7.0, "createdAt": "2026-02-26T11:46:52"}, {"name": "Fear the Invisible Man", "url": "https://ak.sv/movie/8659/fear-the-invisible-man", "image_url": "https://img.downet.net/thumb/178x260/uploads/rPUGv.jpg", "year": 2023, "genre": "اثارة, رعب", "rating": 5.4, "createdAt": "2026-02-26T11:46:52"}, {"name": "Legend of Hawes", "url": "https://ak.sv/movie/8658/legend-of-hawes", "image_url": "https://img.downet.net/thumb/178x260/uploads/EWrg3.jpg", "year": 2022, "genre": "غربي", "rating": 3.1, "createdAt": "2026-02-26T11:46:52"}, {"name": "Cult Hero", "url": "https://ak.sv/movie/8657/cult-hero", "image_url": "https://img.downet.net/thumb/178x260/uploads/cwfVl.jpg", "year": 2022, "genre": "اكشن, اثارة, رعب", "rating": 6.6, "createdAt": "2026-02-26T11:46:52"}, {"name": "The Renata Road", "url": "https://ak.sv/movie/8654/the-renata-road", "image_url": "https://img.downet.net/thumb/178x260/uploads/F7WOl.jpg", "year": 2023, "genre": "اثارة, غموض", "rating": 5.5, "createdAt": "2026-02-26T11:46:52"}, {"name": "Punch", "url": "https://ak.sv/movie/8656/punch", "image_url": "https://img.downet.net/thumb/178x260/uploads/UJMn3.jpg", "year": 2022, "genre": "رياضي, دراما", "rating": 6.6, "createdAt": "2026-02-26T11:46:52"}, {"name": "Hyväveli", "url": "https://ak.sv/movie/8655/hyvveli", "image_url": "https://img.downet.net/thumb/178x260/uploads/XDE78.jpg", "year": 2022, "genre": "دراما", "rating": 5.5, "createdAt": "2026-02-26T11:46:52"}, {"name": "Coast Guard Malaysia: Ops Helang", "url": "https://ak.sv/movie/8648/coast-guard-malaysia-ops-helang-1", "image_url": "https://img.downet.net/thumb/178x260/uploads/AJ0AP.jpg", "year": 2023, "genre": "اكشن, جريمة, مغامرة", "rating": 6.0, "createdAt": "2026-02-26T11:46:52"}, {"name": "Avatar: The Way of Water", "url": "https://ak.sv/movie/7745/avatar-the-way-of-water-13", "image_url": "https://img.downet.net/thumb/178x260/uploads/UujEU.jpg", "year": 2022, "genre": "اكشن, فانتازيا, مغامرة", "rating": 7.7, "createdAt": "2026-02-26T11:46:52"}, {"name": "Plan 75", "url": "https://ak.sv/movie/8639/plan-75", "image_url": "https://img.downet.net/thumb/178x260/uploads/tqHw4.jpg", "year": 2022, "genre": "خيال علمي, دراما", "rating": 6.7, "createdAt": "2026-02-26T11:46:58"}, {"name": "Custody", "url": "https://ak.sv/movie/8640/custody", "image_url": "https://img.downet.net/thumb/178x260/uploads/NtH7X.jpg", "year": 2023, "genre": "اكشن, اثارة, دراما", "rating": 7.1, "createdAt": "2026-02-26T11:46:58"}, {"name": "Dalíland", "url": "https://ak.sv/movie/8629/dalland", "image_url": "https://img.downet.net/thumb/178x260/uploads/iSJ3L.jpeg", "year": 2023, "genre": "سيرة ذاتية, دراما", "rating": 6.3, "createdAt": "2026-02-26T11:46:58"}, {"name": "The Secret Kingdom", "url": "https://ak.sv/movie/8628/the-secret-kingdom", "image_url": "https://img.downet.net/thumb/178x260/uploads/VAQXo.jpg", "year": 2023, "genre": "عائلي, مغامرة", "rating": 7.4, "createdAt": "2026-02-26T11:46:58"}, {"name": "97Minutes", "url": "https://ak.sv/movie/8627/97minutes", "image_url": "https://img.downet.net/thumb/178x260/uploads/zJjjE.jpg", "year": 2023, "genre": "اثارة", "rating": 5.0, "createdAt": "2026-02-26T11:46:58"}, {"name": "Brooklyn 45", "url": "https://ak.sv/movie/8626/brooklyn-45", "image_url": "https://img.downet.net/thumb/178x260/uploads/lAAeI.jpg", "year": 2023, "genre": "تاريخي, دراما, رعب", "rating": 6.6, "createdAt": "2026-02-26T11:46:58"}, {"name": "Bloody Daddy", "url": "https://ak.sv/movie/8624/bloody-daddy", "image_url": "https://img.downet.net/thumb/178x260/uploads/nTqSG.jpg", "year": 2023, "genre": "اكشن, اثارة, دراما", "rating": 8.0, "createdAt": "2026-02-26T11:46:58"}, {"name": "Ghar Banduk Biryani", "url": "https://ak.sv/movie/8623/ghar-banduk-biryani", "image_url": "https://img.downet.net/thumb/178x260/uploads/icuMa.jpg", "year": 2023, "genre": "كوميدي, اثارة, دراما", "rating": 7.5, "createdAt": "2026-02-26T11:46:58"}, {"name": "Bermuda Island", "url": "https://ak.sv/movie/8618/bermuda-island", "image_url": "https://img.downet.net/thumb/178x260/uploads/K95ab.jpg", "year": 2023, "genre": "اكشن, دراما, مغامرة", "rating": 3.8, "createdAt": "2026-02-26T11:46:58"}, {"name": "Flamin' Hot", "url": "https://ak.sv/movie/8622/flamin-hot", "image_url": "https://img.downet.net/thumb/178x260/uploads/LSyqM.jpg", "year": 2023, "genre": "سيرة ذاتية, تاريخي, دراما", "rating": 5.8, "createdAt": "2026-02-26T11:46:58"}, {"name": "The Wonder Weeks", "url": "https://ak.sv/movie/8621/the-wonder-weeks", "image_url": "https://img.downet.net/thumb/178x260/uploads/lqyWA.jpg", "year": 2023, "genre": "NETFLIX, كوميدي, دراما", "rating": 6.0, "createdAt": "2026-02-26T11:46:59"}, {"name": "ميرف كولت", "url": "https://ak.sv/movie/8620/ميرف-كولت", "image_url": "https://img.downet.net/thumb/178x260/uploads/A7WJp.jpg", "year": 2023, "genre": "مدبلج, NETFLIX, كوميدي, رومانسي", "rating": 6.5, "createdAt": "2026-02-26T11:46:59"}, {"name": "Merve Kült", "url": "https://ak.sv/movie/8619/merve-klt", "image_url": "https://img.downet.net/thumb/178x260/uploads/3IvXv.jpg", "year": 2023, "genre": "NETFLIX, كوميدي, رومانسي", "rating": 5.5, "createdAt": "2026-02-26T11:46:59"}, {"name": "The Pope's Exorcist", "url": "https://ak.sv/movie/8322/the-pope-s-exorcist-5", "image_url": "https://img.downet.net/thumb/178x260/uploads/Lk9sX.jpeg", "year": 2023, "genre": "اثارة, رعب", "rating": 6.1, "createdAt": "2026-02-26T11:46:59"}, {"name": "Fear", "url": "https://ak.sv/movie/8154/fear", "image_url": "https://img.downet.net/thumb/178x260/uploads/2W9iv.jpg", "year": 2023, "genre": "رعب", "rating": 3.5, "createdAt": "2026-02-26T11:46:59"}, {"name": "Marooned Awakening", "url": "https://ak.sv/movie/8617/marooned-awakening", "image_url": "https://img.downet.net/thumb/178x260/uploads/nC3z0.jpg", "year": 2022, "genre": "اثارة, غموض, دراما", "rating": 7.0, "createdAt": "2026-02-26T11:46:59"}, {"name": "My Fault", "url": "https://ak.sv/movie/8616/my-fault", "image_url": "https://img.downet.net/thumb/178x260/uploads/QZUCg.jpg", "year": 2023, "genre": "دراما", "rating": 6.2, "createdAt": "2026-02-26T11:46:59"}, {"name": "Pollen", "url": "https://ak.sv/movie/8615/pollen", "image_url": "https://img.downet.net/thumb/178x260/uploads/6ilKW.jpg", "year": 2023, "genre": "رعب", "rating": 4.1, "createdAt": "2026-02-26T11:46:59"}, {"name": "Criminal Network", "url": "https://ak.sv/movie/8614/criminal-network", "image_url": "https://img.downet.net/thumb/178x260/uploads/fIFLX.jpg", "year": 2023, "genre": "دراما, جريمة", "rating": 3.4, "createdAt": "2026-02-26T11:46:59"}, {"name": "The Devil Comes at Night", "url": "https://ak.sv/movie/8613/the-devil-comes-at-night", "image_url": "https://img.downet.net/thumb/178x260/uploads/r0Op8.jpg", "year": 2023, "genre": "رعب", "rating": 5.5, "createdAt": "2026-02-26T11:46:59"}, {"name": "Are You There God? It's Me, Margaret", "url": "https://ak.sv/movie/8612/are-you-there-god-it-s-me-margaret-7", "image_url": "https://img.downet.net/thumb/178x260/uploads/N8YGY.jpg", "year": 2023, "genre": "كوميدي, عائلي, دراما", "rating": 7.8, "createdAt": "2026-02-26T11:46:59"}, {"name": "Somewhere in Queens", "url": "https://ak.sv/movie/8611/somewhere-in-queens-3", "image_url": "https://img.downet.net/thumb/178x260/uploads/xPJZI.jpeg", "year": 2023, "genre": "كوميدي, دراما", "rating": 7.4, "createdAt": "2026-02-26T11:46:59"}, {"name": "Master Gardener", "url": "https://ak.sv/movie/8610/master-gardener-1", "image_url": "https://img.downet.net/thumb/178x260/uploads/IYcbC.jpg", "year": 2022, "genre": "اثارة, دراما", "rating": 6.5, "createdAt": "2026-02-26T11:46:59"}, {"name": "Showing Up", "url": "https://ak.sv/movie/8608/showing-up", "image_url": "https://img.downet.net/thumb/178x260/uploads/cLDQy.jpg", "year": 2022, "genre": "كوميدي, دراما", "rating": 7.1, "createdAt": "2026-02-26T11:46:59"}, {"name": "The Fist of the Condor", "url": "https://ak.sv/movie/8607/the-fist-of-the-condor", "image_url": "https://img.downet.net/thumb/178x260/uploads/pUdTP.jpg", "year": 2023, "genre": "اكشن", "rating": 5.6, "createdAt": "2026-02-26T11:46:59"}, {"name": "Safe Place", "url": "https://ak.sv/movie/8605/safe-place", "image_url": "https://img.downet.net/thumb/178x260/uploads/LXDX9.jpg", "year": 2022, "genre": "دراما", "rating": 7.8, "createdAt": "2026-02-26T11:46:59"}, {"name": "Raaghu", "url": "https://ak.sv/movie/8606/raaghu", "image_url": "https://img.downet.net/thumb/178x260/uploads/waMQI.jpeg", "year": 2023, "genre": "اكشن, اثارة, رعب", "rating": 8.0, "createdAt": "2026-02-26T11:46:59"}, {"name": "Ride On", "url": "https://ak.sv/movie/8604/ride-on", "image_url": "https://img.downet.net/thumb/178x260/uploads/MQ9jg.jpg", "year": 2023, "genre": "اكشن, كوميدي, دراما", "rating": 6.6, "createdAt": "2026-02-26T11:46:59"}, {"name": "Dragon Hunt", "url": "https://ak.sv/movie/8603/dragon-hunt", "image_url": "https://img.downet.net/thumb/178x260/uploads/OTLzo.jpg", "year": 2023, "genre": "اكشن, دراما, مغامرة", "rating": 6.5, "createdAt": "2026-02-26T11:46:59"}, {"name": "The Last Deal", "url": "https://ak.sv/movie/8602/the-last-deal", "image_url": "https://img.downet.net/thumb/178x260/uploads/aZZNB.jpg", "year": 2023, "genre": "اثارة, جريمة", "rating": 6.1, "createdAt": "2026-02-26T11:46:59"}, {"name": "John Wick: Chapter 4", "url": "https://ak.sv/movie/8253/john-wick-chapter-4-13", "image_url": "https://img.downet.net/thumb/178x260/uploads/4nFc1.jpeg", "year": 2023, "genre": "اكشن, اثارة, جريمة", "rating": 8.0, "createdAt": "2026-02-26T11:47:05"}, {"name": "Bora", "url": "https://ak.sv/movie/8599/bora", "image_url": "https://img.downet.net/thumb/178x260/uploads/q74rB.jpg", "year": 2023, "genre": "اثارة", "rating": 5.5, "createdAt": "2026-02-26T11:47:05"}, {"name": "Student Seduction", "url": "https://ak.sv/movie/8598/student-seduction", "image_url": "https://img.downet.net/thumb/178x260/uploads/NjVht.jpg", "year": 2022, "genre": "اثارة, دراما", "rating": 5.5, "createdAt": "2026-02-26T11:47:05"}, {"name": "The Way Out", "url": "https://ak.sv/movie/8597/the-way-out", "image_url": "https://img.downet.net/thumb/178x260/uploads/73DTq.jpg", "year": 2022, "genre": "غموض, دراما, رعب", "rating": 5.9, "createdAt": "2026-02-26T11:47:05"}, {"name": "Subspecies V: Blood Rise", "url": "https://ak.sv/movie/8596/subspecies-v-blood-rise", "image_url": "https://img.downet.net/thumb/178x260/uploads/dEhJx.jpg", "year": 2023, "genre": "رعب", "rating": 8.0, "createdAt": "2026-02-26T11:47:05"}, {"name": "Gumraah", "url": "https://ak.sv/movie/8595/gumraah", "image_url": "https://img.downet.net/thumb/178x260/uploads/onk1I.jpg", "year": 2023, "genre": "اكشن, دراما, جريمة", "rating": 6.5, "createdAt": "2026-02-26T11:47:05"}, {"name": "The Foreigner", "url": "https://ak.sv/movie/8594/the-foreigner", "image_url": "https://img.downet.net/thumb/178x260/uploads/c8hAq.jpg", "year": 2017, "genre": "اكشن, اثارة", "rating": 7.0, "createdAt": "2026-02-26T11:47:05"}, {"name": "Veeram", "url": "https://ak.sv/movie/8593/veeram", "image_url": "https://img.downet.net/thumb/178x260/uploads/iV0or.jpg", "year": 2023, "genre": "اكشن, عائلي, دراما", "rating": 7.7, "createdAt": "2026-02-26T11:47:05"}, {"name": "Mumbaikar", "url": "https://ak.sv/movie/8592/mumbaikar", "image_url": "https://img.downet.net/thumb/178x260/uploads/Hs1U7.jpg", "year": 2023, "genre": "اكشن, اثارة, دراما", "rating": 4.4, "createdAt": "2026-02-26T11:47:05"}, {"name": "Ugram", "url": "https://ak.sv/movie/8591/ugram", "image_url": "https://img.downet.net/thumb/178x260/uploads/ikPct.jpg", "year": 2023, "genre": "اكشن, رومانسي, دراما", "rating": 8.7, "createdAt": "2026-02-26T11:47:05"}, {"name": "Benaqaab Chehre", "url": "https://ak.sv/movie/8590/benaqaab-chehre", "image_url": "https://img.downet.net/thumb/178x260/uploads/ySRo9.jpeg", "year": 2023, "genre": "اكشن, جريمة", "rating": 5.5, "createdAt": "2026-02-26T11:47:05"}, {"name": "Phalana Abbayi Phalana Ammayi", "url": "https://ak.sv/movie/8589/phalana-abbayi-phalana-ammayi", "image_url": "https://img.downet.net/thumb/178x260/uploads/eHsjf.jpg", "year": 2023, "genre": "عائلي, رومانسي, دراما", "rating": 5.1, "createdAt": "2026-02-26T11:47:05"}, {"name": "Shooting Stars", "url": "https://ak.sv/movie/8588/shooting-stars", "image_url": "https://img.downet.net/thumb/178x260/uploads/iiF66.jpg", "year": 2023, "genre": "سيرة ذاتية, تاريخي, دراما", "rating": 6.3, "createdAt": "2026-02-26T11:47:05"}, {"name": "Follow Her", "url": "https://ak.sv/movie/8587/follow-her", "image_url": "https://img.downet.net/thumb/178x260/uploads/7cZWe.jpg", "year": 2023, "genre": "اثارة", "rating": 6.2, "createdAt": "2026-02-26T11:47:05"}, {"name": "Mercy", "url": "https://ak.sv/movie/8586/mercy", "image_url": "https://img.downet.net/thumb/178x260/uploads/C6IZ4.jpg", "year": 2023, "genre": "اكشن", "rating": 5.9, "createdAt": "2026-02-26T11:47:05"}, {"name": "Buddy Games: Spring Awakening", "url": "https://ak.sv/movie/8585/buddy-games-spring-awakening", "image_url": "https://img.downet.net/thumb/178x260/uploads/CRHOr.jpg", "year": 2023, "genre": "كوميدي", "rating": 6.4, "createdAt": "2026-02-26T11:47:05"}, {"name": "World War III", "url": "https://ak.sv/movie/8584/world-war-iii", "image_url": "https://img.downet.net/thumb/178x260/uploads/otga8.jpg", "year": 2022, "genre": "دراما, جريمة, مغامرة", "rating": 7.0, "createdAt": "2026-02-26T11:47:05"}, {"name": "Fool's Paradise", "url": "https://ak.sv/movie/8583/fool-s-paradise", "image_url": "https://img.downet.net/thumb/178x260/uploads/7BStU.jpg", "year": 2023, "genre": "كوميدي", "rating": 5.1, "createdAt": "2026-02-26T11:47:05"}, {"name": "BlackBerry", "url": "https://ak.sv/movie/8582/blackberry", "image_url": "https://img.downet.net/thumb/178x260/uploads/Sjce9.jpg", "year": 2023, "genre": "كوميدي, سيرة ذاتية, دراما", "rating": 7.8, "createdAt": "2026-02-26T11:47:06"}, {"name": "Padre Pio", "url": "https://ak.sv/movie/8581/padre-pio-2", "image_url": "https://img.downet.net/thumb/178x260/uploads/qQUMQ.jpg", "year": 2022, "genre": "سيرة ذاتية, دراما", "rating": 6.4, "createdAt": "2026-02-26T11:47:06"}, {"name": "Medellin", "url": "https://ak.sv/movie/8580/medellin", "image_url": "https://img.downet.net/thumb/178x260/uploads/NUZCM.jpg", "year": 2023, "genre": "كوميدي", "rating": 4.9, "createdAt": "2026-02-26T11:47:06"}, {"name": "Missed Connections", "url": "https://ak.sv/movie/8579/missed-connections", "image_url": "https://img.downet.net/thumb/178x260/uploads/WRnyL.jpg", "year": 2023, "genre": "كوميدي, رومانسي, NETFLIX", "rating": 5.5, "createdAt": "2026-02-26T11:47:06"}, {"name": "Rich in Love 2", "url": "https://ak.sv/movie/8578/rich-in-love-2", "image_url": "https://img.downet.net/thumb/178x260/uploads/13gPh.jpg", "year": 2023, "genre": "كوميدي, موسيقى, رومانسي", "rating": 5.5, "createdAt": "2026-02-26T11:47:06"}, {"name": "The Super Mario Bros. Movie", "url": "https://ak.sv/movie/8311/the-super-mario-bros-movie", "image_url": "https://img.downet.net/thumb/178x260/uploads/mOnoG.jpg", "year": 2023, "genre": "انمي, كوميدي, مغامرة", "rating": 7.2, "createdAt": "2026-02-26T11:47:06"}, {"name": "The Haunting 2", "url": "https://ak.sv/movie/8577/the-haunting-2", "image_url": "https://img.downet.net/thumb/178x260/uploads/pdjT9.jpg", "year": 2023, "genre": "اثارة, غموض, رعب", "rating": 5.5, "createdAt": "2026-02-26T11:47:06"}, {"name": "The Haunting", "url": "https://ak.sv/movie/8576/the-haunting", "image_url": "https://img.downet.net/thumb/178x260/uploads/tEttF.jpg", "year": 2023, "genre": "اثارة, غموض", "rating": 5.5, "createdAt": "2026-02-26T11:47:06"}, {"name": "A Beautiful Life", "url": "https://ak.sv/movie/8574/a-beautiful-life", "image_url": "https://img.downet.net/thumb/178x260/uploads/ZVdf1.jpg", "year": 2023, "genre": "NETFLIX, موسيقى, رومانسي, دراما", "rating": 6.2, "createdAt": "2026-02-26T11:47:06"}, {"name": "Firenado", "url": "https://ak.sv/movie/8572/firenado", "image_url": "https://img.downet.net/thumb/178x260/uploads/nxR1M.jpg", "year": 2023, "genre": "اكشن", "rating": 4.3, "createdAt": "2026-02-26T11:47:06"}, {"name": "عبود على الحدود", "url": "https://ak.sv/movie/8571/عبود-على-الحدود", "image_url": "https://img.downet.net/thumb/178x260/uploads/bpbQ5.jpg", "year": 1999, "genre": "كوميدي", "rating": 7.6, "createdAt": "2026-02-26T11:47:06"}, {"name": "Mixed by Erry", "url": "https://ak.sv/movie/8570/mixed-by-erry", "image_url": "https://img.downet.net/thumb/178x260/uploads/3JMXH.jpg", "year": 2023, "genre": "كوميدي", "rating": 7.5, "createdAt": "2026-02-26T11:47:06"}, {"name": "Book Club: The Next Chapter", "url": "https://ak.sv/movie/8569/book-club-the-next-chapter", "image_url": "https://img.downet.net/thumb/178x260/uploads/UjU3D.jpg", "year": 2023, "genre": "كوميدي", "rating": 5.7, "createdAt": "2026-02-26T11:47:12"}, {"name": "Mojave Diamonds", "url": "https://ak.sv/movie/8568/mojave-diamonds-5", "image_url": "https://img.downet.net/thumb/178x260/uploads/XwauP.jpg", "year": 2023, "genre": "اكشن, اثارة", "rating": 6.5, "createdAt": "2026-02-26T11:47:12"}, {"name": "Monica", "url": "https://ak.sv/movie/8567/monica", "image_url": "https://img.downet.net/thumb/178x260/uploads/Z1WaU.jpg", "year": 2022, "genre": "دراما", "rating": 6.5, "createdAt": "2026-02-26T11:47:12"}, {"name": "Wolf Warrior 2", "url": "https://ak.sv/movie/8566/wolf-warrior-2", "image_url": "https://img.downet.net/thumb/178x260/uploads/OfNjh.jpg", "year": 2017, "genre": "اكشن, دراما, مغامرة", "rating": 5.9, "createdAt": "2026-02-26T11:47:12"}, {"name": "Wolf Warrior", "url": "https://ak.sv/movie/8565/wolf-warrior", "image_url": "https://img.downet.net/thumb/178x260/uploads/Xixb1.jpg", "year": 2015, "genre": "اكشن, اثارة, جريمة", "rating": 5.3, "createdAt": "2026-02-26T11:47:12"}, {"name": "Reality", "url": "https://ak.sv/movie/8564/reality", "image_url": "https://img.downet.net/thumb/178x260/uploads/5tivx.jpg", "year": 2023, "genre": "دراما", "rating": 6.8, "createdAt": "2026-02-26T11:47:12"}, {"name": "The Black Demon", "url": "https://ak.sv/movie/8562/the-black-demon", "image_url": "https://img.downet.net/thumb/178x260/uploads/MXHfF.jpg", "year": 2023, "genre": "اثارة, خيال علمي, رعب", "rating": 4.0, "createdAt": "2026-02-26T11:47:12"}, {"name": "Rebel", "url": "https://ak.sv/movie/8560/rebel", "image_url": "https://img.downet.net/thumb/178x260/uploads/9KFve.jpg", "year": 2022, "genre": "اكشن, اثارة, دراما", "rating": 7.6, "createdAt": "2026-02-26T11:47:12"}, {"name": "MobKing", "url": "https://ak.sv/movie/8561/mobking", "image_url": "https://img.downet.net/thumb/178x260/uploads/ooi8O.jpg", "year": 2023, "genre": "اثارة, دراما", "rating": 6.7, "createdAt": "2026-02-26T11:47:12"}, {"name": "Credimi", "url": "https://ak.sv/movie/8559/credimi", "image_url": "https://img.downet.net/thumb/178x260/uploads/aR2a5.jpg", "year": 2022, "genre": "عائلي, فانتازيا, دراما", "rating": 5.5, "createdAt": "2026-02-26T11:47:12"}, {"name": "Nightmare Radio: The Night Stalker", "url": "https://ak.sv/movie/8558/nightmare-radio-the-night-stalker", "image_url": "https://img.downet.net/thumb/178x260/uploads/fvoCh.jpg", "year": 2023, "genre": "رعب", "rating": 3.9, "createdAt": "2026-02-26T11:47:13"}, {"name": "Wolf Garden", "url": "https://ak.sv/movie/8557/wolf-garden", "image_url": "https://img.downet.net/thumb/178x260/uploads/tUwkh.jpg", "year": 2023, "genre": "اثارة, رعب", "rating": 7.3, "createdAt": "2026-02-26T11:47:13"}, {"name": "The Warrant: Breaker's Law", "url": "https://ak.sv/movie/8556/the-warrant-breaker-s-law", "image_url": "https://img.downet.net/thumb/178x260/uploads/ZWhYf.jpg", "year": 2023, "genre": "اثارة, غربي", "rating": 5.5, "createdAt": "2026-02-26T11:47:13"}, {"name": "Scream 4", "url": "https://ak.sv/movie/8554/scream-4", "image_url": "https://img.downet.net/thumb/178x260/uploads/HWlOi.jpg", "year": 2011, "genre": "غموض, رعب", "rating": 6.2, "createdAt": "2026-02-26T11:47:13"}, {"name": "Scream 3", "url": "https://ak.sv/movie/8553/scream-3", "image_url": "https://img.downet.net/thumb/178x260/uploads/wA9vk.jpg", "year": 2000, "genre": "غموض, رعب", "rating": 5.6, "createdAt": "2026-02-26T11:47:13"}, {"name": "Scream 2", "url": "https://ak.sv/movie/8552/scream-2", "image_url": "https://img.downet.net/thumb/178x260/uploads/zD8KL.jpg", "year": 1997, "genre": "غموض, رعب", "rating": 6.3, "createdAt": "2026-02-26T11:47:13"}, {"name": "Scream", "url": "https://ak.sv/movie/8551/scream", "image_url": "https://img.downet.net/thumb/178x260/uploads/XOwJM.jpg", "year": 1996, "genre": "غموض, رعب", "rating": 7.4, "createdAt": "2026-02-26T11:47:13"}, {"name": "Cherry", "url": "https://ak.sv/movie/8555/cherry", "image_url": "https://img.downet.net/thumb/178x260/uploads/q0l6E.jpg", "year": 2022, "genre": "كوميدي, دراما", "rating": 5.9, "createdAt": "2026-02-26T11:47:13"}, {"name": "دنانير", "url": "https://ak.sv/movie/8550/دنانير", "image_url": "https://img.downet.net/thumb/178x260/uploads/WYvHp.jpg", "year": 1940, "genre": "موسيقى, رومانسي, تاريخي", "rating": 7.2, "createdAt": "2026-02-26T11:47:13"}, {"name": "There Will Be Blood", "url": "https://ak.sv/movie/8549/there-will-be-blood", "image_url": "https://img.downet.net/thumb/178x260/uploads/E1Pqu.jpg", "year": 2007, "genre": "دراما", "rating": 8.2, "createdAt": "2026-02-26T11:47:13"}, {"name": "Eat Pray Love", "url": "https://ak.sv/movie/8548/eat-pray-love", "image_url": "https://img.downet.net/thumb/178x260/uploads/basLC.jpg", "year": 2010, "genre": "سيرة ذاتية, رومانسي, دراما", "rating": 5.8, "createdAt": "2026-02-26T11:47:13"}, {"name": "Ponniyin Selvan: Part Two", "url": "https://ak.sv/movie/8547/ponniyin-selvan-part-two", "image_url": "https://img.downet.net/thumb/178x260/uploads/ZDwOz.jpg", "year": 2023, "genre": "اكشن, دراما, مغامرة", "rating": 8.0, "createdAt": "2026-02-26T11:47:13"}, {"name": "Secret Agent Dingledorf and His Trusty Dog Splat", "url": "https://ak.sv/movie/8545/secret-agent-dingledorf-and-his-trusty-dog-splat", "image_url": "https://img.downet.net/thumb/178x260/uploads/Obqit.jpg", "year": 22, "genre": "كوميدي, عائلي", "rating": 5.7, "createdAt": "2026-02-26T11:47:13"}, {"name": "The Year of the Dog", "url": "https://ak.sv/movie/8546/the-year-of-the-dog", "image_url": "https://img.downet.net/thumb/178x260/uploads/6BdMP.jpg", "year": 2022, "genre": "دراما", "rating": 8.7, "createdAt": "2026-02-26T11:47:13"}, {"name": "Gatlopp", "url": "https://ak.sv/movie/8544/gatlopp-7", "image_url": "https://img.downet.net/thumb/178x260/uploads/DlzwK.jpg", "year": 2022, "genre": "كوميدي, رعب", "rating": 6.0, "createdAt": "2026-02-26T11:47:13"}, {"name": "The Girl Who Believes in Miracles", "url": "https://ak.sv/movie/8543/the-girl-who-believes-in-miracles", "image_url": "https://img.downet.net/thumb/178x260/uploads/awBoJ.jpg", "year": 2021, "genre": "عائلي, دراما", "rating": 5.6, "createdAt": "2026-02-26T11:47:13"}, {"name": "Dark Nature", "url": "https://ak.sv/movie/8542/dark-nature", "image_url": "https://img.downet.net/thumb/178x260/uploads/WpN9X.jpg", "year": 2022, "genre": "رعب", "rating": 6.0, "createdAt": "2026-02-26T11:47:13"}, {"name": "Ghosty", "url": "https://ak.sv/movie/8541/ghosty", "image_url": "https://img.downet.net/thumb/178x260/uploads/IyLrC.jpg", "year": 2023, "genre": "كوميدي, دراما, رعب", "rating": 3.8, "createdAt": "2026-02-26T11:47:13"}, {"name": "Bhediya", "url": "https://ak.sv/movie/8540/bhediya", "image_url": "https://img.downet.net/thumb/178x260/uploads/UvEZr.jpg", "year": 2022, "genre": "كوميدي, اثارة, رعب", "rating": 7.2, "createdAt": "2026-02-26T11:47:13"}, {"name": "Blood and Gold", "url": "https://ak.sv/movie/8539/blood-and-gold", "image_url": "https://img.downet.net/thumb/178x260/uploads/xZD4m.jpg", "year": 2023, "genre": "اكشن, NETFLIX, كوميدي, دراما", "rating": 6.8, "createdAt": "2026-02-26T11:47:13"}, {"name": "Tin and Tina", "url": "https://ak.sv/movie/8538/tin-and-tina", "image_url": "https://img.downet.net/thumb/178x260/uploads/7QSHE.jpg", "year": 2023, "genre": "اثارة, غموض, رعب", "rating": 6.5, "createdAt": "2026-02-26T11:47:18"}, {"name": "Where the Tracks End", "url": "https://ak.sv/movie/8537/where-the-tracks-end", "image_url": "https://img.downet.net/thumb/178x260/uploads/kaARx.jpg", "year": 2023, "genre": "NETFLIX, كوميدي, عائلي, دراما", "rating": 5.5, "createdAt": "2026-02-26T11:47:18"}, {"name": "Influencer", "url": "https://ak.sv/movie/8536/influencer", "image_url": "https://img.downet.net/thumb/178x260/uploads/lNEdW.jpg", "year": 2022, "genre": "اثارة, غموض, رعب", "rating": 7.5, "createdAt": "2026-02-26T11:47:18"}, {"name": "What Remains", "url": "https://ak.sv/movie/8535/what-remains", "image_url": "https://img.downet.net/thumb/178x260/uploads/n6mSp.jpg", "year": 2022, "genre": "اثارة, غموض, دراما", "rating": 6.4, "createdAt": "2026-02-26T11:47:18"}, {"name": "Malum", "url": "https://ak.sv/movie/8534/malum", "image_url": "https://img.downet.net/thumb/178x260/uploads/sUvHN.jpg", "year": 2023, "genre": "اثارة, دراما, رعب", "rating": 5.9, "createdAt": "2026-02-26T11:47:18"}, {"name": "Dungeons & Dragons: Honor Among Thieves", "url": "https://ak.sv/movie/8400/dungeons-dragons-honor-among-thieves-11", "image_url": "https://img.downet.net/thumb/178x260/uploads/UJJ7O.jpg", "year": 2023, "genre": "اكشن, كوميدي, مغامرة", "rating": 7.4, "createdAt": "2026-02-26T11:47:18"}, {"name": "Skinford: Death Sentence", "url": "https://ak.sv/movie/8533/skinford-death-sentence", "image_url": "https://img.downet.net/thumb/178x260/uploads/r2BzS.jpg", "year": 2023, "genre": "اثارة, رعب", "rating": 5.3, "createdAt": "2026-02-26T11:47:18"}, {"name": "Operation Mayfair", "url": "https://ak.sv/movie/8532/operation-mayfair", "image_url": "https://img.downet.net/thumb/178x260/uploads/uQTHP.jpg", "year": 2023, "genre": "اثارة, جريمة", "rating": 7.0, "createdAt": "2026-02-26T11:47:19"}, {"name": "Fangs Out", "url": "https://ak.sv/movie/8531/fangs-out", "image_url": "https://img.downet.net/thumb/178x260/uploads/1xfaB.jpg", "year": 2023, "genre": "رعب", "rating": 2.2, "createdAt": "2026-02-26T11:47:19"}, {"name": "فيلم 65", "url": "https://ak.sv/movie/8272/فيلم-65", "image_url": "https://img.downet.net/thumb/178x260/uploads/iexxw.jpg", "year": 2023, "genre": "اكشن, دراما, مغامرة", "rating": 5.4, "createdAt": "2026-02-26T11:47:19"}, {"name": "Consecration", "url": "https://ak.sv/movie/8161/consecration", "image_url": "https://img.downet.net/thumb/178x260/uploads/xtmJA.jpg", "year": 2023, "genre": "اثارة, رعب", "rating": 5.1, "createdAt": "2026-02-26T11:47:19"}, {"name": "Last Sentinel", "url": "https://ak.sv/movie/8371/last-sentinel", "image_url": "https://img.downet.net/thumb/178x260/uploads/3YzO1.jpg", "year": 2023, "genre": "غموض, خيال علمي", "rating": 5.0, "createdAt": "2026-02-26T11:47:19"}, {"name": "Top Gear", "url": "https://ak.sv/movie/8530/top-gear", "image_url": "https://img.downet.net/thumb/178x260/uploads/BUMLz.jpg", "year": 2022, "genre": "اكشن, رومانسي, دراما", "rating": 7.8, "createdAt": "2026-02-26T11:47:19"}, {"name": "Sirf Ek Bandaa Kaafi Hai", "url": "https://ak.sv/movie/8529/sirf-ek-bandaa-kaafi-hai", "image_url": "https://img.downet.net/thumb/178x260/uploads/Dv8MV.jpg", "year": 2023, "genre": "اكشن, دراما", "rating": 8.1, "createdAt": "2026-02-26T11:47:19"}, {"name": "Virupaksha", "url": "https://ak.sv/movie/8528/virupaksha", "image_url": "https://img.downet.net/thumb/178x260/uploads/1obqM.jpg", "year": 2023, "genre": "اكشن, غموض, دراما", "rating": 7.7, "createdAt": "2026-02-26T11:47:19"}, {"name": "Mother’s Day", "url": "https://ak.sv/movie/8527/mothers-day", "image_url": "https://img.downet.net/thumb/178x260/uploads/jF6Ru.jpg", "year": 2023, "genre": "اكشن, اثارة, دراما", "rating": 6.3, "createdAt": "2026-02-26T11:47:19"}, {"name": "Bheed", "url": "https://ak.sv/movie/8526/bheed", "image_url": "https://img.downet.net/thumb/178x260/uploads/68O9O.jpg", "year": 2023, "genre": "تاريخي, دراما", "rating": 7.7, "createdAt": "2026-02-26T11:47:19"}, {"name": "Hard Feelings", "url": "https://ak.sv/movie/8525/hard-feelings", "image_url": "https://img.downet.net/thumb/178x260/uploads/vAx2M.jpg", "year": 2023, "genre": "NETFLIX, كوميدي", "rating": 5.5, "createdAt": "2026-02-26T11:47:19"}, {"name": "Love Again", "url": "https://ak.sv/movie/8524/love-again", "image_url": "https://img.downet.net/thumb/178x260/uploads/JGJ1w.jpg", "year": 2023, "genre": "كوميدي, رومانسي, دراما", "rating": 6.0, "createdAt": "2026-02-26T11:47:19"}, {"name": "Creed II", "url": "https://ak.sv/movie/8523/creed-ii", "image_url": "https://img.downet.net/thumb/178x260/uploads/tvSER.jpg", "year": 2018, "genre": "اكشن, رياضي, دراما", "rating": 7.1, "createdAt": "2026-02-26T11:47:19"}, {"name": "Creed", "url": "https://ak.sv/movie/8522/creed", "image_url": "https://img.downet.net/thumb/178x260/uploads/uMpqE.jpg", "year": 2015, "genre": "اكشن, رياضي, دراما", "rating": 7.6, "createdAt": "2026-02-26T11:47:19"}, {"name": "The Swan Princess: A Fairytale Is Born", "url": "https://ak.sv/movie/8519/the-swan-princess-a-fairytale-is-born", "image_url": "https://img.downet.net/thumb/178x260/uploads/ySwvC.jpg", "year": 2023, "genre": "انمي, كوميدي, مغامرة", "rating": 5.5, "createdAt": "2026-02-26T11:47:19"}, {"name": "Victim Suspect", "url": "https://ak.sv/movie/8521/victim-suspect", "image_url": "https://img.downet.net/thumb/178x260/uploads/2JJ1L.jpg", "year": 2023, "genre": "وثائقي, جريمة", "rating": 7.9, "createdAt": "2026-02-26T11:47:19"}, {"name": "Hearts and Horses", "url": "https://ak.sv/movie/8520/hearts-and-horses", "image_url": "https://img.downet.net/thumb/178x260/uploads/W8iDv.jpg", "year": 2023, "genre": "عائلي", "rating": 4.6, "createdAt": "2026-02-26T11:47:19"}, {"name": "Gentleman", "url": "https://ak.sv/movie/8518/gentleman", "image_url": "https://img.downet.net/thumb/178x260/uploads/eQatH.jpg", "year": 2022, "genre": "اكشن, دراما, جريمة", "rating": 6.0, "createdAt": "2026-02-26T11:47:19"}, {"name": "The Antarctic Octopus", "url": "https://ak.sv/movie/8517/the-antarctic-octopus", "image_url": "https://img.downet.net/thumb/178x260/uploads/FzQHD.jpg", "year": 2023, "genre": "اكشن, خيال علمي", "rating": 5.5, "createdAt": "2026-02-26T11:47:19"}, {"name": "Spirit Puppet", "url": "https://ak.sv/movie/8516/spirit-puppet", "image_url": "https://img.downet.net/thumb/178x260/uploads/J6kDj.jpg", "year": 2023, "genre": "اثارة, غموض", "rating": 5.5, "createdAt": "2026-02-26T11:47:19"}, {"name": "47Ronin", "url": "https://ak.sv/movie/8512/47ronin", "image_url": "https://img.downet.net/thumb/178x260/uploads/wsNaW.jpg", "year": 2013, "genre": "اكشن, فانتازيا, دراما", "rating": 6.2, "createdAt": "2026-02-26T11:47:19"}, {"name": "Teeth", "url": "https://ak.sv/movie/8515/teeth", "image_url": "https://img.downet.net/thumb/178x260/uploads/qR5ys.jpg", "year": 2007, "genre": "كوميدي, فانتازيا, رعب", "rating": 5.4, "createdAt": "2026-02-26T11:47:19"}]